misugaru/__init__.py
misugaru/cli.py
misugaru/confidence.py
misugaru/core.py
misugaru/data.py
misugaru/score.py
misugaru/train.py
misugaru-0.1.11.dist-info/METADATA
misugaru-0.1.11.dist-info/WHEEL
misugaru-0.1.11.dist-info/entry_points.txt
misugaru-0.1.11.dist-info/licenses/LICENSE
misugaru-0.1.11.dist-info/RECORD
