Metadata-Version: 2.3
Name: misugaru
Version: 0.1.11
Summary: A mokapot wrapper with high protein content
Author-email: Siegfried Gessulat <siegfried.gessulat@msaid.de>
Maintainer-email: Siegfried Gessulat <siegfried.gessulat@msaid.de>
License:                     GNU GENERAL PUBLIC LICENSE
Keywords: FDR,confidence,proteomics
Requires-Python: >=3.10
Requires-Dist: jupyter>=1.1.1
Requires-Dist: mokapot
Requires-Dist: numba>=0.60.0
Requires-Dist: numpy>=2.0.2
Requires-Dist: pandas>=2.2.3
Requires-Dist: typer>=0.15.1
